misosoup/__init__.py
misosoup/main.py
misosoup/utilities.py
misosoup/examples/example_output.yaml
misosoup/examples/media_mbm_no_co2_hco3.yaml
misosoup/examples/strains/A1R12.xml
misosoup/examples/strains/I2R16.xml
misosoup/examples/strains/I3M07.xml
misosoup/library/__init__.py
misosoup/library/analysis.py
misosoup/library/common.py
misosoup/library/getters.py
misosoup/library/load.py
misosoup/library/minimizer.py
misosoup/library/readwrite.py
misosoup/library/solutions.py
misosoup/library/solve.py
misosoup/library/validate.py
misosoup/reframed/__init__.py
misosoup/reframed/gurobi_env_solver.py
misosoup/reframed/layered_community.py
misosoup-2.3.2.dist-info/licenses/LICENSE.md
misosoup-2.3.2.dist-info/METADATA
misosoup-2.3.2.dist-info/WHEEL
misosoup-2.3.2.dist-info/entry_points.txt
misosoup-2.3.2.dist-info/top_level.txt
misosoup-2.3.2.dist-info/RECORD
