Metadata-Version: 2.4
Name: misosoup
Version: 2.3.2
Home-page: https://github.com/sirno/misosoup
Author: Nicolas Ochsner
Author-email: nicolas.ochsner@env.ethz.ch
License: MIT
Requires-Python: >=3.9
License-File: LICENSE.md
Requires-Dist: reframed>=1.6.0
Requires-Dist: scipy
Requires-Dist: gurobipy
Requires-Dist: pyyaml>=6.0
Requires-Dist: pandas
Requires-Dist: pyarrow
Provides-Extra: dev
Requires-Dist: pylint; extra == "dev"
Requires-Dist: pytest; extra == "dev"
Requires-Dist: tox; extra == "dev"
Requires-Dist: black; extra == "dev"
Dynamic: license-file
